assessment/SCTAssessmentReportTemplate.html
assessment/__init__.py
assessment/assessment.py
assessment/awssctcomplexitymatrix.csv
assessment/sct_input.csv
mock/__init__.py
mock/mock.py
dcg_extensionmigrationassistant-1.0.1.dist-info/LICENSE.txt
dcg_extensionmigrationassistant-1.0.1.dist-info/METADATA
dcg_extensionmigrationassistant-1.0.1.dist-info/WHEEL
dcg_extensionmigrationassistant-1.0.1.dist-info/entry_points.txt
dcg_extensionmigrationassistant-1.0.1.dist-info/top_level.txt
dcg_extensionmigrationassistant-1.0.1.dist-info/RECORD
